{"labelsTree": [{"id": 6, "text": "Notes", "descriptions": null, "parentId": -1, "Subject": "Subject", "Grade": "SS1", "Curriculum": "NERDC", "subject": "Clothing And Textiles", "subLabels": [{"id": 7, "text": "(1) career opportunities", "descriptions": [], "parentId": 6, "Subject": "Subject", "Grade": "SS1", "Curriculum": "NERDC", "subject": "Clothing And Textiles", "subLabels": []}, {"id": 8, "text": "In", "descriptions": [], "parentId": 6, "Subject": "Subject", "Grade": "SS1", "Curriculum": "NERDC", "subject": "Clothing And Textiles", "subLabels": [{"id": 9, "text": "Clothing and textiles", "descriptions": [], "parentId": 8, "Subject": "Subject", "Grade": "SS1", "Curriculum": "NERDC", "subject": "Clothing And Textiles", "subLabels": []}, {"id": 10, "text": "(i)   career types", "descriptions": [], "parentId": 8, "Subject": "Subject", "Grade": "SS1", "Curriculum": "NERDC", "subject": "Clothing And Textiles", "subLabels": []}, {"id": 11, "text": "(i)    work ethics", "descriptions": [], "parentId": 8, "Subject": "Subject", "Grade": "SS1", "Curriculum": "NERDC", "subject": "Clothing And Textiles", "subLabels": []}, {"id": 12, "text": "(2)   fibre and fabric", "descriptions": [], "parentId": 8, "Subject": "Subject", "Grade": "SS1", "Curriculum": "NERDC", "subject": "Clothing And Textiles", "subLabels": []}, {"id": 13, "text": "(3)   clothing", "descriptions": [], "parentId": 8, "Subject": "Subject", "Grade": "SS1", "Curriculum": "NERDC", "subject": "Clothing And Textiles", "subLabels": []}, {"id": 14, "text": "(4)     wardrobe planning ", "descriptions": [], "parentId": 8, "Subject": "Subject", "Grade": "SS1", "Curriculum": "NERDC", "subject": "Clothing And Textiles", "subLabels": []}]}]}], "labels": [{"id": 6, "text": "Notes", "descriptions": null, "parentId": -1, "Subject": "Subject", "Grade": "SS1", "Curriculum": "NERDC", "subject": "Clothing And Textiles", "subLabels": [{"id": 7, "text": "(1) career opportunities", "descriptions": [], "parentId": 6, "Subject": "Subject", "Grade": "SS1", "Curriculum": "NERDC", "subject": "Clothing And Textiles", "subLabels": []}, {"id": 8, "text": "In", "descriptions": [], "parentId": 6, "Subject": "Subject", "Grade": "SS1", "Curriculum": "NERDC", "subject": "Clothing And Textiles", "subLabels": [{"id": 9, "text": "Clothing and textiles", "descriptions": [], "parentId": 8, "Subject": "Subject", "Grade": "SS1", "Curriculum": "NERDC", "subject": "Clothing And Textiles", "subLabels": []}, {"id": 10, "text": "(i)   career types", "descriptions": [], "parentId": 8, "Subject": "Subject", "Grade": "SS1", "Curriculum": "NERDC", "subject": "Clothing And Textiles", "subLabels": []}, {"id": 11, "text": "(i)    work ethics", "descriptions": [], "parentId": 8, "Subject": "Subject", "Grade": "SS1", "Curriculum": "NERDC", "subject": "Clothing And Textiles", "subLabels": []}, {"id": 12, "text": "(2)   fibre and fabric", "descriptions": [], "parentId": 8, "Subject": "Subject", "Grade": "SS1", "Curriculum": "NERDC", "subject": "Clothing And Textiles", "subLabels": []}, {"id": 13, "text": "(3)   clothing", "descriptions": [], "parentId": 8, "Subject": "Subject", "Grade": "SS1", "Curriculum": "NERDC", "subject": "Clothing And Textiles", "subLabels": []}, {"id": 14, "text": "(4)     wardrobe planning ", "descriptions": [], "parentId": 8, "Subject": "Subject", "Grade": "SS1", "Curriculum": "NERDC", "subject": "Clothing And Textiles", "subLabels": []}]}]}, {"id": 7, "text": "(1) career opportunities", "descriptions": [], "parentId": 6, "Subject": "Subject", "Grade": "SS1", "Curriculum": "NERDC", "subject": "Clothing And Textiles", "subLabels": []}, {"id": 8, "text": "In", "descriptions": [], "parentId": 6, "Subject": "Subject", "Grade": "SS1", "Curriculum": "NERDC", "subject": "Clothing And Textiles", "subLabels": [{"id": 9, "text": "Clothing and textiles", "descriptions": [], "parentId": 8, "Subject": "Subject", "Grade": "SS1", "Curriculum": "NERDC", "subject": "Clothing And Textiles", "subLabels": []}, {"id": 10, "text": "(i)   career types", "descriptions": [], "parentId": 8, "Subject": "Subject", "Grade": "SS1", "Curriculum": "NERDC", "subject": "Clothing And Textiles", "subLabels": []}, {"id": 11, "text": "(i)    work ethics", "descriptions": [], "parentId": 8, "Subject": "Subject", "Grade": "SS1", "Curriculum": "NERDC", "subject": "Clothing And Textiles", "subLabels": []}, {"id": 12, "text": "(2)   fibre and fabric", "descriptions": [], "parentId": 8, "Subject": "Subject", "Grade": "SS1", "Curriculum": "NERDC", "subject": "Clothing And Textiles", "subLabels": []}, {"id": 13, "text": "(3)   clothing", "descriptions": [], "parentId": 8, "Subject": "Subject", "Grade": "SS1", "Curriculum": "NERDC", "subject": "Clothing And Textiles", "subLabels": []}, {"id": 14, "text": "(4)     wardrobe planning ", "descriptions": [], "parentId": 8, "Subject": "Subject", "Grade": "SS1", "Curriculum": "NERDC", "subject": "Clothing And Textiles", "subLabels": []}]}, {"id": 9, "text": "Clothing and textiles", "descriptions": [], "parentId": 8, "Subject": "Subject", "Grade": "SS1", "Curriculum": "NERDC", "subject": "Clothing And Textiles", "subLabels": []}, {"id": 10, "text": "(i)   career types", "descriptions": [], "parentId": 8, "Subject": "Subject", "Grade": "SS1", "Curriculum": "NERDC", "subject": "Clothing And Textiles", "subLabels": []}, {"id": 11, "text": "(i)    work ethics", "descriptions": [], "parentId": 8, "Subject": "Subject", "Grade": "SS1", "Curriculum": "NERDC", "subject": "Clothing And Textiles", "subLabels": []}, {"id": 12, "text": "(2)   fibre and fabric", "descriptions": [], "parentId": 8, "Subject": "Subject", "Grade": "SS1", "Curriculum": "NERDC", "subject": "Clothing And Textiles", "subLabels": []}, {"id": 13, "text": "(3)   clothing", "descriptions": [], "parentId": 8, "Subject": "Subject", "Grade": "SS1", "Curriculum": "NERDC", "subject": "Clothing And Textiles", "subLabels": []}, {"id": 14, "text": "(4)     wardrobe planning ", "descriptions": [], "parentId": 8, "Subject": "Subject", "Grade": "SS1", "Curriculum": "NERDC", "subject": "Clothing And Textiles", "subLabels": []}]}