{
 "subject": "Building Construction",
 "Grade": "None",
 "Curriculum": "NERDC",
 "labelsTree": [
  {
   "id": 8,
   "text": "Suggested reading list",
   "descriptions": null,
   "parentId": -1,
   "subLabels": [
    {
     "id": 9,
     "text": "1 2 3 4 5 6 7 8 9 10 11 12",
     "descriptions": [
      "Stephen Emmitt and Christopher A. Gorse.",
      "M. O. Obande",
      "R. Barry",
      "Ivor H. Seeley",
      "S. C. O. A. Ezeji",
      "Nash",
      "R.  Chudley",
      "W. B. Mckay",
      "Roger Greeno",
      "Adesokan and  M. O. Adeniyi",
      "R. Chuelley",
      "C. M. H. Barritt"
     ],
     "parentId": 8,
     "subLabels": []
    }
   ]
  }
 ],
 "labels": [
  {
   "id": 8,
   "text": "Suggested reading list",
   "descriptions": null,
   "parentId": -1,
   "subLabels": [
    {
     "id": 9,
     "text": "1 2 3 4 5 6 7 8 9 10 11 12",
     "descriptions": [
      "Stephen Emmitt and Christopher A. Gorse.",
      "M. O. Obande",
      "R. Barry",
      "Ivor H. Seeley",
      "S. C. O. A. Ezeji",
      "Nash",
      "R.  Chudley",
      "W. B. Mckay",
      "Roger Greeno",
      "Adesokan and  M. O. Adeniyi",
      "R. Chuelley",
      "C. M. H. Barritt"
     ],
     "parentId": 8,
     "subLabels": []
    }
   ]
  },
  {
   "id": 9,
   "text": "1 2 3 4 5 6 7 8 9 10 11 12",
   "descriptions": [
    "Stephen Emmitt and Christopher A. Gorse.",
    "M. O. Obande",
    "R. Barry",
    "Ivor H. Seeley",
    "S. C. O. A. Ezeji",
    "Nash",
    "R.  Chudley",
    "W. B. Mckay",
    "Roger Greeno",
    "Adesokan and  M. O. Adeniyi",
    "R. Chuelley",
    "C. M. H. Barritt"
   ],
   "parentId": 8,
   "subLabels": []
  }
 ]
}